myloginpath.py
myloginpath-0.0.4.dist-info/AUTHORS
myloginpath-0.0.4.dist-info/LICENSE.txt
myloginpath-0.0.4.dist-info/METADATA
myloginpath-0.0.4.dist-info/WHEEL
myloginpath-0.0.4.dist-info/top_level.txt
myloginpath-0.0.4.dist-info/RECORD
