Metadata-Version: 2.1
Name: myloginpath
Version: 0.0.4
Summary: MySQL login path file reader
Author-email: Inada Naoki <songofacandy@gmail.com>
License: MIT License
Project-URL: Project, https://github.com/PyMySQL/myloginpath/
Keywords: MySQL
Classifier: Development Status :: 5 - Production/Stable
Classifier: Environment :: Other Environment
Classifier: License :: OSI Approved :: MIT License
Classifier: Operating System :: OS Independent
Classifier: Programming Language :: Python
Classifier: Programming Language :: Python :: 3
Classifier: Programming Language :: Python :: 3.7
Classifier: Programming Language :: Python :: 3.8
Classifier: Programming Language :: Python :: 3.9
Classifier: Programming Language :: Python :: 3.10
Classifier: Programming Language :: Python :: 3.11
Classifier: Topic :: Database
Requires-Python: >=3.7
License-File: LICENSE.txt
License-File: AUTHORS
Requires-Dist: cryptography
